opentelemetry/contrib-instrumentations/version.py
opentelemetry_contrib_instrumentations-0.60b1.dist-info/METADATA
opentelemetry_contrib_instrumentations-0.60b1.dist-info/WHEEL
opentelemetry_contrib_instrumentations-0.60b1.dist-info/licenses/LICENSE
opentelemetry_contrib_instrumentations-0.60b1.dist-info/RECORD
