Metadata-Version: 2.4
Name: opentelemetry-contrib-instrumentations
Version: 0.60b1
Summary: OpenTelemetry Contrib Instrumentation Packages
Project-URL: Homepage, https://github.com/open-telemetry/opentelemetry-python-contrib/tree/main/opentelemetry-contrib-instrumentations
Project-URL: Repository, https://github.com/open-telemetry/opentelemetry-python-contrib
Author-email: OpenTelemetry Authors <cncf-opentelemetry-contributors@lists.cncf.io>
License-Expression: Apache-2.0
License-File: LICENSE
Classifier: Development Status :: 4 - Beta
Classifier: Intended Audience :: Developers
Classifier: License :: OSI Approved :: Apache Software License
Classifier: Programming Language :: Python
Classifier: Programming Language :: Python :: 3
Classifier: Programming Language :: Python :: 3.9
Classifier: Programming Language :: Python :: 3.10
Classifier: Programming Language :: Python :: 3.11
Classifier: Programming Language :: Python :: 3.12
Classifier: Programming Language :: Python :: 3.13
Requires-Python: >=3.9
Requires-Dist: opentelemetry-instrumentation-aio-pika==0.60b1
Requires-Dist: opentelemetry-instrumentation-aiohttp-client==0.60b1
Requires-Dist: opentelemetry-instrumentation-aiohttp-server==0.60b1
Requires-Dist: opentelemetry-instrumentation-aiokafka==0.60b1
Requires-Dist: opentelemetry-instrumentation-aiopg==0.60b1
Requires-Dist: opentelemetry-instrumentation-asgi==0.60b1
Requires-Dist: opentelemetry-instrumentation-asyncclick==0.60b1
Requires-Dist: opentelemetry-instrumentation-asyncio==0.60b1
Requires-Dist: opentelemetry-instrumentation-asyncpg==0.60b1
Requires-Dist: opentelemetry-instrumentation-aws-lambda==0.60b1
Requires-Dist: opentelemetry-instrumentation-boto3sqs==0.60b1
Requires-Dist: opentelemetry-instrumentation-boto==0.60b1
Requires-Dist: opentelemetry-instrumentation-botocore==0.60b1
Requires-Dist: opentelemetry-instrumentation-cassandra==0.60b1
Requires-Dist: opentelemetry-instrumentation-celery==0.60b1
Requires-Dist: opentelemetry-instrumentation-click==0.60b1
Requires-Dist: opentelemetry-instrumentation-confluent-kafka==0.60b1
Requires-Dist: opentelemetry-instrumentation-dbapi==0.60b1
Requires-Dist: opentelemetry-instrumentation-django==0.60b1
Requires-Dist: opentelemetry-instrumentation-elasticsearch==0.60b1
Requires-Dist: opentelemetry-instrumentation-falcon==0.60b1
Requires-Dist: opentelemetry-instrumentation-fastapi==0.60b1
Requires-Dist: opentelemetry-instrumentation-flask==0.60b1
Requires-Dist: opentelemetry-instrumentation-grpc==0.60b1
Requires-Dist: opentelemetry-instrumentation-httpx==0.60b1
Requires-Dist: opentelemetry-instrumentation-jinja2==0.60b1
Requires-Dist: opentelemetry-instrumentation-kafka-python==0.60b1
Requires-Dist: opentelemetry-instrumentation-logging==0.60b1
Requires-Dist: opentelemetry-instrumentation-mysql==0.60b1
Requires-Dist: opentelemetry-instrumentation-mysqlclient==0.60b1
Requires-Dist: opentelemetry-instrumentation-pika==0.60b1
Requires-Dist: opentelemetry-instrumentation-psycopg2==0.60b1
Requires-Dist: opentelemetry-instrumentation-psycopg==0.60b1
Requires-Dist: opentelemetry-instrumentation-pymemcache==0.60b1
Requires-Dist: opentelemetry-instrumentation-pymongo==0.60b1
Requires-Dist: opentelemetry-instrumentation-pymssql==0.60b1
Requires-Dist: opentelemetry-instrumentation-pymysql==0.60b1
Requires-Dist: opentelemetry-instrumentation-pyramid==0.60b1
Requires-Dist: opentelemetry-instrumentation-redis==0.60b1
Requires-Dist: opentelemetry-instrumentation-remoulade==0.60b1
Requires-Dist: opentelemetry-instrumentation-requests==0.60b1
Requires-Dist: opentelemetry-instrumentation-sqlalchemy==0.60b1
Requires-Dist: opentelemetry-instrumentation-sqlite3==0.60b1
Requires-Dist: opentelemetry-instrumentation-starlette==0.60b1
Requires-Dist: opentelemetry-instrumentation-system-metrics==0.60b1
Requires-Dist: opentelemetry-instrumentation-threading==0.60b1
Requires-Dist: opentelemetry-instrumentation-tornado==0.60b1
Requires-Dist: opentelemetry-instrumentation-tortoiseorm==0.60b1
Requires-Dist: opentelemetry-instrumentation-urllib3==0.60b1
Requires-Dist: opentelemetry-instrumentation-urllib==0.60b1
Requires-Dist: opentelemetry-instrumentation-wsgi==0.60b1
